birdbath/__init__.py
birdbath/apps.py
birdbath/models.py
birdbath/settings.py
birdbath/system_checks.py
birdbath/checks/__init__.py
birdbath/checks/base.py
birdbath/checks/contrib/__init__.py
birdbath/checks/contrib/heroku.py
birdbath/management/__init__.py
birdbath/management/commands/__init__.py
birdbath/management/commands/run_birdbath.py
birdbath/migrations/0001_initial.py
birdbath/migrations/__init__.py
birdbath/processors/__init__.py
birdbath/processors/base.py
birdbath/processors/users.py
birdbath/processors/contrib/__init__.py
birdbath/processors/contrib/wagtail.py
django_birdbath-2.0.1.dist-info/LICENSE
django_birdbath-2.0.1.dist-info/WHEEL
django_birdbath-2.0.1.dist-info/METADATA
django_birdbath-2.0.1.dist-info/RECORD
