Metadata-Version: 2.1
Name: django-birdbath
Version: 2.0.1
Summary: A simple tool for giving Django database data a good wash. Anonymise user data, delete stuff you
Keywords: django,anonymization,data cleaning
Author-email: Torchbox <info@torchbox.com>
Requires-Python: >=3.9
Classifier: License :: OSI Approved :: BSD License
Classifier: Programming Language :: Python :: 3
Classifier: Programming Language :: Python :: 3.9
Classifier: Programming Language :: Python :: 3.10
Classifier: Programming Language :: Python :: 3.11
Classifier: Programming Language :: Python :: 3.12
Classifier: Programming Language :: Python :: 3.13
Requires-Dist: Faker>=8
Requires-Dist: Django>=4.2
Requires-Dist: django~=4.2 ; extra == "dev"
Requires-Dist: pre-commit>=3.8.0 ; extra == "dev"
Requires-Dist: pytest~=8.3 ; extra == "dev"
Requires-Dist: pytest-django~=4.9 ; extra == "dev"
Requires-Dist: ruff==0.6.9 ; extra == "dev"
Requires-Dist: wagtail~=5.2 ; extra == "dev"
Project-URL: Home, https://github.com/torchbox/django-birdbath
Provides-Extra: dev
